README.md
setup.py
src/swergio/__init__.py
src/swergio/client.py
src/swergio/messageType.py
src/swergio/server.py
src/swergio.egg-info/PKG-INFO
src/swergio.egg-info/SOURCES.txt
src/swergio.egg-info/dependency_links.txt
src/swergio.egg-info/requires.txt
src/swergio.egg-info/top_level.txt