Metadata-Version: 2.1
Name: swergio
Version: 0.0.2
Summary: Swergio Package
Home-page: https://github.com/swergio/swergio
Author: Ishmagurca
License: UNKNOWN
Platform: UNKNOWN
Classifier: Programming Language :: Python :: 3
Classifier: Operating System :: OS Independent
Requires-Python: >=3.6
Provides-Extra: toolbox
